coluroma/__init__.py
coluroma/colors.py
coluroma-3.0.4.dist-info/LICENSE
coluroma-3.0.4.dist-info/METADATA
coluroma-3.0.4.dist-info/WHEEL
coluroma-3.0.4.dist-info/top_level.txt
coluroma-3.0.4.dist-info/RECORD
